torscope/__init__.py
torscope/cache.py
torscope/cli.py
torscope/cli_helpers.py
torscope/microdesc.py
torscope/output.py
torscope/path.py
torscope/utils.py
torscope/api/__init__.py
torscope/api/app.py
torscope/api/geoip.py
torscope/api/models/__init__.py
torscope/api/models/circuit.py
torscope/api/models/common.py
torscope/api/models/directory.py
torscope/api/models/hidden_service.py
torscope/api/routes/__init__.py
torscope/api/routes/circuit.py
torscope/api/routes/directory.py
torscope/api/routes/hidden_service.py
torscope/api/websocket/__init__.py
torscope/api/websocket/handlers.py
torscope/api/websocket/manager.py
torscope/crypto/__init__.py
torscope/crypto/proof_of_work.py
torscope/directory/__init__.py
torscope/directory/authority.py
torscope/directory/bridge.py
torscope/directory/certificates.py
torscope/directory/client.py
torscope/directory/client_auth.py
torscope/directory/consensus.py
torscope/directory/descriptor.py
torscope/directory/exit_policy.py
torscope/directory/extra_info.py
torscope/directory/fallback.py
torscope/directory/hs_descriptor.py
torscope/directory/hsdir.py
torscope/directory/microdescriptor.py
torscope/directory/models.py
torscope/directory/or_client.py
torscope/onion/__init__.py
torscope/onion/address.py
torscope/onion/cell.py
torscope/onion/circuit.py
torscope/onion/connection.py
torscope/onion/hs_ntor.py
torscope/onion/ntor.py
torscope/onion/ntor_v3.py
torscope/onion/relay.py
torscope/onion/rendezvous.py
torscope/onion/transport.py
torscope/onion/obfs4/__init__.py
torscope/onion/obfs4/elligator.py
torscope/onion/obfs4/framing.py
torscope/onion/obfs4/handshake.py
torscope/onion/obfs4/socket_wrapper.py
torscope/onion/obfs4/transport.py
torscope/parser/__init__.py
torscope-0.8.0.dist-info/licenses/LICENSE
torscope-0.8.0.dist-info/METADATA
torscope-0.8.0.dist-info/WHEEL
torscope-0.8.0.dist-info/entry_points.txt
torscope-0.8.0.dist-info/top_level.txt
torscope-0.8.0.dist-info/RECORD
