Metadata-Version: 2.4
Name: torscope
Version: 0.8.0
Summary: A tool for exploring the Tor network
Author-email: Mete Balci <metebalci@gmail.com>
License-Expression: GPL-3.0-or-later
Project-URL: Homepage, https://github.com/metebalci/torscope
Project-URL: Documentation, https://torscope.readthedocs.io
Project-URL: Repository, https://github.com/metebalci/torscope
Project-URL: Issues, https://github.com/metebalci/torscope/issues
Keywords: tor,onion,routing,privacy,anonymity,network,information,explore
Classifier: Development Status :: 3 - Alpha
Classifier: Intended Audience :: Developers
Classifier: Intended Audience :: System Administrators
Classifier: Programming Language :: Python :: 3
Classifier: Programming Language :: Python :: 3.12
Classifier: Programming Language :: Python :: 3.13
Classifier: Topic :: Security :: Cryptography
Classifier: Topic :: System :: Networking
Classifier: Topic :: Internet
Requires-Python: >=3.12
License-File: LICENSE
Requires-Dist: httpx>=0.25.0
Requires-Dist: cryptography>=41.0.0
Requires-Dist: pynacl>=1.5.0
Requires-Dist: ge25519>=1.3.0
Requires-Dist: siphash>=0.0.1
Provides-Extra: api
Requires-Dist: fastapi>=0.109.0; extra == "api"
Requires-Dist: uvicorn[standard]>=0.27.0; extra == "api"
Requires-Dist: websockets>=12.0; extra == "api"
Requires-Dist: geoip2>=4.8.0; extra == "api"
Provides-Extra: dev
Requires-Dist: torscope[api]; extra == "dev"
Requires-Dist: build; extra == "dev"
Requires-Dist: twine; extra == "dev"
Requires-Dist: pytest>=7.0; extra == "dev"
Requires-Dist: pytest-cov>=4.0; extra == "dev"
Requires-Dist: pytest-asyncio>=0.23.0; extra == "dev"
Requires-Dist: black>=23.0; extra == "dev"
Requires-Dist: ruff>=0.1.0; extra == "dev"
Requires-Dist: mypy>=1.0; extra == "dev"
Requires-Dist: zstandard>=0.22.0; extra == "dev"
Dynamic: license-file
